permitio/__init__.py
permitio/api.py
permitio-0.0.1.dist-info/METADATA
permitio-0.0.1.dist-info/WHEEL
permitio-0.0.1.dist-info/top_level.txt
permitio-0.0.1.dist-info/RECORD
