Metadata-Version: 2.1
Name: permitio
Version: 0.0.1
Summary: permitio python sdk
Home-page: UNKNOWN
Author: Or Weis, Asaf Cohen
Author-email: asaf@authorizon.com
License: UNKNOWN
Platform: UNKNOWN
Classifier: Operating System :: OS Independent
Classifier: Programming Language :: Python
Classifier: Programming Language :: Python :: 3
Classifier: Programming Language :: Python :: 3.8
Classifier: Programming Language :: Python :: 3.9
Requires-Python: >=3.8
Requires-Dist: requests (==2.20.0)
Requires-Dist: urllib3 (==1.24.2)
